src/apb_i2c_bridge.v
`timescale 1ns / 1ps

module apb_i2c_bridge (
    // AMBA APB Interface
    input  wire        pclk,      // System clock
    input  wire        presetn,   // Active-low reset
    input  wire        psel,      // Peripheral select
    input  wire        penable,   // Enable signal (Access phase)
    input  wire        pwrite,    // Direction (1=Write, 0=Read)
    input  wire [7:0]  paddr,     // Register Address
    input  wire [7:0]  pwdata,    // Write data
    output reg  [7:0]  prdata,    // Read data
    output reg         pready,    // Ready signal (stall the bus if busy)

    // I2C Physical Interface
    output reg         scl,       // I2C Clock
    input  wire        sda_in,    // I2C Data Input
    output reg         sda_out,   // I2C Data Output
    output reg         sda_oe     // I2C Data Output Enable (1 = Drive, 0 = High-Z)
);

    // FSM State Encodings (Using localparam for clean synthesis)
    localparam IDLE       = 3'b000;
    localparam START      = 3'b001;
    localparam DATA_SHIFT = 3'b010;
    localparam ACK_PHASE  = 3'b011;
    localparam STOP       = 3'b100;

    reg [2:0] state;
    reg [7:0] shift_reg;
    reg [2:0] bit_cnt;    // Counts 0 to 7 (8 bits)

    // Main FSM Sequential Logic
    always @(posedge pclk or negedge presetn) begin
        if (!presetn) begin
            state    <= IDLE;
            pready   <= 1'b1;
            scl      <= 1'b1;
            sda_out  <= 1'b1;
            sda_oe   <= 1'b1; // Drive high by default
            bit_cnt  <= 3'd7;
            prdata   <= 8'h00;
        end else begin
            case (state)
                IDLE: begin
                    pready  <= 1'b1;  // Bus is free
                    scl     <= 1'b1;
                    sda_out <= 1'b1;
                    sda_oe  <= 1'b1;
                    
                    // Detect APB Access Phase (Valid request)
                    if (psel && penable) begin
                        pready    <= 1'b0; // STALL THE APB BUS IMMEDIATELY
                        shift_reg <= pwdata; 
                        state     <= START;
                    end
                end

                START: begin
                    sda_out <= 1'b0; // I2C Start Condition: SDA goes low while SCL is high
                    state   <= DATA_SHIFT;
                    bit_cnt <= 3'd7; // Reset bit counter for MSB first
                end

                DATA_SHIFT: begin
                    scl <= ~scl; // Toggle I2C Clock
                    
                    if (!scl) begin
                        // When SCL is LOW: Change Data
                        sda_out <= shift_reg[bit_cnt];
                    end else begin
                        // When SCL is HIGH: Data is stable, slave reads it
                        if (bit_cnt == 0) begin
                            state <= ACK_PHASE;
                        end else begin
                            bit_cnt <= bit_cnt - 1;
                        end
                    end
                end

                ACK_PHASE: begin
                    scl <= ~scl; // Continue clocking
                    
                    if (!scl) begin
                        // Release SDA line (High-Z) so slave can pull it low to ACK
                        sda_oe <= 1'b0; 
                    end else begin
                        // Sample the ACK here in a full implementation
                        // For this bridge, we transition to STOP
                        state <= STOP;
                    end
                end

                STOP: begin
                    scl     <= 1'b1;
                    sda_oe  <= 1'b1; // Take control of SDA back
                    sda_out <= 1'b1; // I2C Stop Condition: SDA goes high while SCL is high
                    
                    pready  <= 1'b1; // UNSTALL THE APB BUS
                    state   <= IDLE;
                end
                
                default: state <= IDLE;
            endcase
        end
    end

endmodule

tb/tb_apb_i2c.v
`timescale 1ns / 1ps

module tb_apb_i2c;

    // 1. Declare Testbench Signals
    reg        pclk;
    reg        presetn;
    reg        psel;
    reg        penable;
    reg        pwrite;
    reg  [7:0] paddr;
    reg  [7:0] pwdata;
    wire [7:0] prdata;
    wire       pready;

    wire       scl;
    reg        sda_in;
    wire       sda_out;
    wire       sda_oe;

    // 2. Instantiate the Bridge (Device Under Test)
    apb_i2c_bridge uut (
        .pclk(pclk),
        .presetn(presetn),
        .psel(psel),
        .penable(penable),
        .pwrite(pwrite),
        .paddr(paddr),
        .pwdata(pwdata),
        .prdata(prdata),
        .pready(pready),
        .scl(scl),
        .sda_in(sda_in),
        .sda_out(sda_out),
        .sda_oe(sda_oe)
    );

    // 3. Generate System Clock (50MHz -> 20ns period)
    always #10 pclk = ~pclk;

    // 4. Main Simulation Block
    initial begin
        // Setup VCD generation for GTKWave
        $dumpfile("runs/apb_i2c_waves.vcd");
        $dumpvars(0, tb_apb_i2c);

        // Initialize all signals
        pclk    = 0;
        presetn = 0;
        psel    = 0;
        penable = 0;
        pwrite  = 0;
        paddr   = 8'h00;
        pwdata  = 8'h00;
        sda_in  = 1; // Simulate the physical I2C pull-up resistor

        // Apply Reset
        #25 presetn = 1;
        #20;

        // ==========================================
        // SIMULATE A PROCESSOR WRITE TRANSACTION
        // We want to send the hex value 0xA5 (10100101 in binary)
        // ==========================================

        // Phase 1: APB SETUP PHASE
        @(posedge pclk);
        psel   = 1;
        pwrite = 1;
        paddr  = 8'h10; // Target sensor register address
        pwdata = 8'hA5; // The data payload

        // Phase 2: APB ACCESS PHASE
        @(posedge pclk);
        penable = 1;

        // Phase 3: WAIT-STATE INSERTION
        // The bridge will immediately pull 'pready' to 0 here.
        // We use a Verilog wait() statement to pause our simulated 
        // WE wait until pready is 0 since we encountered a bug where for the shifting phase it was going from 1->0 but it didn;t wait as it was waiting for it to get back high again which it was already
        wait(pready == 1'b0);
	// wait for the bridge to finish the slow I2C transaction and pull pready high
	wait(pready == 1'b1);

        // Phase 4: TRANSACTION COMPLETE
        @(posedge pclk);
        psel    = 0;
        penable = 0;
        pwrite  = 0;

        // Let the simulation run a little longer to observe the I2C STOP condition
        #100;
        $display("Simulation Complete: APB to I2C transfer successful.");
        $finish;
    end

endmodule

runs/apb_i2c_waves.vcd
$date
	Fri Mar 27 00:18:48 2026
$end
$version
	Icarus Verilog
$end
$timescale
	1ps
$end
$scope module tb_apb_i2c $end
$var wire 1 ! sda_out $end
$var wire 1 " sda_oe $end
$var wire 1 # scl $end
$var wire 1 $ pready $end
$var wire 8 % prdata [7:0] $end
$var reg 8 & paddr [7:0] $end
$var reg 1 ' pclk $end
$var reg 1 ( penable $end
$var reg 1 ) presetn $end
$var reg 1 * psel $end
$var reg 8 + pwdata [7:0] $end
$var reg 1 , pwrite $end
$var reg 1 - sda_in $end
$scope module uut $end
$var wire 8 . paddr [7:0] $end
$var wire 1 ' pclk $end
$var wire 1 ( penable $end
$var wire 1 ) presetn $end
$var wire 1 * psel $end
$var wire 8 / pwdata [7:0] $end
$var wire 1 , pwrite $end
$var wire 1 - sda_in $end
$var parameter 3 0 ACK_PHASE $end
$var parameter 3 1 DATA_SHIFT $end
$var parameter 3 2 IDLE $end
$var parameter 3 3 START $end
$var parameter 3 4 STOP $end
$var reg 3 5 bit_cnt [2:0] $end
$var reg 8 6 prdata [7:0] $end
$var reg 1 $ pready $end
$var reg 1 # scl $end
$var reg 1 " sda_oe $end
$var reg 1 ! sda_out $end
$var reg 8 7 shift_reg [7:0] $end
$var reg 3 8 state [2:0] $end
$upscope $end
$upscope $end
$enddefinitions $end
$comment Show the parameter values. $end
$dumpall
b100 4
b1 3
b0 2
b10 1
b11 0
$end
#0
$dumpvars
b0 8
bx 7
b0 6
b111 5
b0 /
b0 .
1-
0,
b0 +
0*
0)
0(
0'
b0 &
b0 %
1$
1#
1"
1!
$end
#10000
1'
#20000
0'
#25000
1)
#30000
1'
#40000
0'
#50000
b10100101 +
b10100101 /
b10000 &
b10000 .
1,
1*
1'
#60000
0'
#70000
b1 8
b10100101 7
0$
1(
1'
#80000
0'
#90000
b10 8
0!
1'
#100000
0'
#110000
b110 5
0#
1'
#120000
0'
#130000
1#
1'
#140000
0'
#150000
b101 5
0#
1'
#160000
0'
#170000
1!
1#
1'
#180000
0'
#190000
b100 5
0#
1'
#200000
0'
#210000
0!
1#
1'
#220000
0'
#230000
b11 5
0#
1'
#240000
0'
#250000
1#
1'
#260000
0'
#270000
b10 5
0#
1'
#280000
0'
#290000
1!
1#
1'
#300000
0'
#310000
b1 5
0#
1'
#320000
0'
#330000
0!
1#
1'
#340000
0'
#350000
b0 5
0#
1'
#360000
0'
#370000
1!
1#
1'
#380000
0'
#390000
b11 8
0#
1'
#400000
0'
#410000
0"
1#
1'
#420000
0'
#430000
b100 8
0#
1'
#440000
0'
#450000
b0 8
1$
1"
1#
1'
#460000
0'
#470000
0,
0(
0*
1'
